{"id": "6adb9c71-8321-4ceb-ab6f-d6fbc74b1ed8", "filename": "COCO_train2014_000000000113.jpg", "datetime": "2017-05-15 00:00:00", "entityList": "(cup),(person),(person),(cake),(knife),(person),(cup),(cup),(chair),(dining table),(cup),(chair),(cup),(cup),", "entitySpatialMeta": "(cup,0.1643701,0.7139964,0.29454297,0.8174453,0.9995016),(person,0.012036298,0.056284666,0.38655105,0.74276036,0.9989786),(person,0.35533974,0.07922224,0.8159484,0.67962015,0.99870074),(cake,0.37076673,0.66428703,0.97238976,0.89042073,0.9965295),(knife,0.6094971,0.57053965,0.72748274,0.7058291,0.9942654),(person,0.82079875,0.14414528,1.0,0.68185455,0.9928052),(cup,0.67998844,0.096373625,0.7474854,0.14376366,0.98882884),(cup,0.6757693,0.14743282,0.74399054,0.18867864,0.983835),(chair,0.20145953,0.59359735,0.5956601,0.70321476,0.95479834),(dining table,0.06478109,0.61183745,1.0,0.97465986,0.94155484),(cup,0.8208707,0.14820643,0.8873646,0.18729857,0.7878128),(chair,0.034796234,0.904303,0.19945344,1.0,0.6289841),(cup,0.41901556,0.16500285,0.46464747,0.2065047,0.52848387),(cup,0.83068544,0.10221155,0.88621724,0.13802464,0.30339113),", "spatialRelationList": "", "semanticRelationList": "", "location": "Somalia", "device": "", "packed_caption": "a man cutting a cake with a knife .[0.003627551853902901]|a man and a woman cutting a cake .[0.00227226153987902]|a woman cutting a cake with a knife .[0.0016784647090891428]|a man and a woman cutting a cake together .[0.0013763232617240836]|a man and woman cutting a cake together .[0.0011728535300985976]|a man cutting a cake on top of a table .[0.0011241656733470644]|a man and woman cutting a cake with a knife .[0.0011143605313260962]|a man cutting a cake with a sword .[0.0011101552634192582]|a man cutting into a cake with a knife .[0.0008666198485061799]|a man and a woman cutting a cake with a knife .[0.0008113164467255247]|a man standing next to a woman cutting a cake .[0.0007760566196819562]|a woman cutting a cake with a sword .[0.0007660869567975763]|a man is cutting a cake with a knife .[0.0007133635415164123]|a man and woman cutting a cake on a table .[0.0007002300198222292]|a man and a woman cutting a cake[0.0006188261896250729]|a man cutting a birthday cake with a knife .[0.0005399029594200794]|a man cutting a cake with a knife[0.0005393928205350474]|a man and woman cutting a cake with a sword .[0.0004897235829894487]|a man and a woman cutting a cake on a table .[0.00045576261363712903]|a man and a woman cutting a cake with a sword .[0.0004024242785114492]|\n", "captions": ["a man cutting a cake with a knife .", "a man and a woman cutting a cake .", "a woman cutting a cake with a knife .", "a man and a woman cutting a cake together .", "a man and woman cutting a cake together .", "a man cutting a cake on top of a table .", "a man and woman cutting a cake with a knife .", "a man cutting a cake with a sword .", "a man cutting into a cake with a knife .", "a man and a woman cutting a cake with a knife .", "a man standing next to a woman cutting a cake .", "a woman cutting a cake with a sword .", "a man is cutting a cake with a knife .", "a man and woman cutting a cake on a table .", "a man and a woman cutting a cake", "a man cutting a birthday cake with a knife .", "a man cutting a cake with a knife", "a man and woman cutting a cake with a sword .", "a man and a woman cutting a cake on a table .", "a man and a woman cutting a cake with a sword ."]}